{
	"logs": {
		"debug": false
	},
	"level": {
		"0": "错误",
		"1": "警告",
		"2": "消息",
		"3": "测试"
	},
	"errors": {
		"E0010": "数据库连接失败：%v",
		"E0011": "无法找到指定的SQL语句：%s",
		"E0012": "数据库表插入错误：%v",
		"E0013": "数据库表查询错误：%v",
		"E0014": "扫描数据库查询结果集错误：%v",
		"E0015": "查询SQL文件错误：%v",
		"E0016": "创建表失败：%v",
		"E0017": "打开SQL文件失败：%v",
		"E0018": "读取SQL文件错误：%v",
		"E0019": "SQL文件格式错误：%v",
		"E0020": "无法找到%s的高度记录",
		"E0021": "数据库表更新错误：%v",
		"E0022": "JSON转字符串失败：%v",
		"E0023": "字符串转JSON失败：%v",
		"E0024": "HTTP请求失败：%v",
		"E0025": "HTTP返回提解析失败：%v",
		"E0026": "区块链请求错误：%v",
		"E0029": "无法将字符串转化为数字：%s",
		"E0030": "更新数据库却没有指定有效的更新字段",
		"E0031": "请求账户余额失败：%v",
		"E0032": "构建手续费失败：%v",
		"E0033": "解锁用户账户失败，请检查密码是否正确：%v",
		"E0034": "获取手续费失败：%v",
		"E0035": "发送交易失败：%v",
		"E0036": "获取新地址失败：%v",
		"E0037": "获取交易失败：%v",
		"E0038": "获取可用提币ID失败：%v",
		"E0039": "获取所有未稳定提币交易失败：%v",
		"E0040": "从链上获取的信息为空",
		"E0041": "解析链上的数字错误：%v"
	},
	"warnings": {
		"W0001": "指定块未包含交易",
		"W0036": "使用了错误的请求method，要求：%s；实际：%s",
		"W0037": "未找到指定的Path：%s",
		"W0038": "提交的参数错误：%v"
	},
	"information": {
		"I0": "这是一条测试信息"
	},
	"debugs": {
		"D0": "Debug一下：%v"
	}
}